{"cameraMode":{"drawMode":0,"name":"Shaded","section":"Shading Mode"},"sceneLighting":true,"audioPlay":false,"sceneViewState":{"m_AlwaysRefresh":false,"showFog":true,"showSkybox":true,"showFlares":true,"showImageEffects":true,"showParticleSystems":true,"showVisualEffectGraphs":true,"m_FxEnabled":true},"in2DMode":false,"pivot":{"x":-0.2969589829444885,"y":4.229991912841797,"z":14.138829231262207},"rotation":{"x":0.044608425348997119,"y":-0.6453266739845276,"z":0.03779485449194908,"w":0.7616685032844544},"size":12.10326099395752,"orthographic":false}